tools/build_cffi.py
box2d_testbed/base_test.py
box2d_testbed/shader.py
box2d_testbed/tb_events.py
box2d_testbed/tb_benchmark.py
box2d_testbed/tb_shapes.py
box2d_testbed/ui.py
box2d_testbed/__init__.py
box2d_testbed/testbed_state.py
box2d_testbed/tb_collision.py
box2d_testbed/shared.py
box2d_testbed/testbed_simulation.py
box2d_testbed/testbed.py
box2d_testbed/debug_draw_gl.py
box2d_testbed/draw.py
box2d_testbed/tb_joints.py
box2d_testbed/shaders/solid_polygon.fs
box2d_testbed/shaders/solid_circle.vs
box2d_testbed/shaders/circle.vs
box2d_testbed/shaders/solid_capsule.fs
box2d_testbed/shaders/background.vs
box2d_testbed/shaders/circle.fs
box2d_testbed/shaders/background.fs
box2d_testbed/shaders/solid_capsule.vs
box2d_testbed/shaders/solid_polygon.vs
box2d_testbed/shaders/solid_polygon_debug.vs
box2d_testbed/shaders/solid_circle.fs
box2d_python-0.1.2.dist-info/LICENSE-Box2D
box2d_python-0.1.2.dist-info/RECORD
box2d_python-0.1.2.dist-info/LICENSE
box2d_python-0.1.2.dist-info/WHEEL
box2d_python-0.1.2.dist-info/entry_points.txt
box2d_python-0.1.2.dist-info/top_level.txt
box2d_python-0.1.2.dist-info/METADATA
box2d/shape_def.py
box2d/world.py
box2d/body.py
box2d/debug_draw.py
box2d/__init__.py
box2d/_box2d.abi3.so
box2d/collision_filter.py
box2d/joint.py
box2d/shape.py
box2d/math.py
