Metadata-Version: 2.2
Name: box2d-python
Version: 0.1.2
Summary: Bindings for box2d v3
Author-email: Giorgos Giagas <giorgosg@gmail.com>
Maintainer-email: Giorgos Giagas <giorgosg@gmail.com>
License: MIT
Classifier: Programming Language :: Python :: 3
Classifier: License :: OSI Approved :: MIT License
Classifier: Operating System :: OS Independent
Requires-Python: >=3.12
License-File: LICENSE
License-File: LICENSE-Box2D
Requires-Dist: cffi>=1.16.0
Provides-Extra: testbed
Requires-Dist: imgui_bundle; extra == "testbed"
Requires-Dist: PyOpenGL; extra == "testbed"
Requires-Dist: PyOpenGL-accelerate; extra == "testbed"
Requires-Dist: numpy; extra == "testbed"
